flake8_annotations/__init__.py
flake8_annotations/ast_walker.py
flake8_annotations/checker.py
flake8_annotations/enums.py
flake8_annotations/error_codes.py
flake8_annotations-3.1.0.dist-info/LICENSE
flake8_annotations-3.1.0.dist-info/METADATA
flake8_annotations-3.1.0.dist-info/WHEEL
flake8_annotations-3.1.0.dist-info/entry_points.txt
flake8_annotations-3.1.0.dist-info/RECORD
