Metadata-Version: 2.1
Name: flake8-annotations
Version: 3.1.0
Summary: Flake8 Type Annotation Checks
Home-page: https://github.com/sco1/flake8-annotations
License: MIT
Author: S Co1
Author-email: sco1.git@gmail.com
Requires-Python: >=3.8.1
Classifier: Development Status :: 5 - Production/Stable
Classifier: Environment :: Console
Classifier: Framework :: Flake8
Classifier: Intended Audience :: Developers
Classifier: License :: OSI Approved :: MIT License
Classifier: Operating System :: OS Independent
Classifier: Programming Language :: Python
Classifier: Programming Language :: Python :: 3
Classifier: Programming Language :: Python :: 3.9
Classifier: Programming Language :: Python :: 3.10
Classifier: Programming Language :: Python :: 3.11
Classifier: Programming Language :: Python :: 3.12
Classifier: Programming Language :: Python :: 3 :: Only
Classifier: Programming Language :: Python :: 3.13
Classifier: Programming Language :: Python :: 3.8
Classifier: Topic :: Software Development :: Libraries :: Python Modules
Classifier: Topic :: Software Development :: Quality Assurance
Classifier: Typing :: Typed
Requires-Dist: attrs (>=21.4)
Requires-Dist: flake8 (>=5.0)
Project-URL: Issue Tracker, https://github.com/sco1/flake8-annotations/issues
Project-URL: Repository, https://github.com/sco1/flake8-annotations
